{"33070610000135": {"Acct Number": 33070610000135.0, "Sol": 3300.0, "Region": "Sehore", "Branch": "Rajgarh", "Cust Id": 382609.0, "Acct Name": "Nirbhay Pushapad So Mohan Lal Pushapad", "Comm Add 1": "Near Shanker Dharmshala Ghoom Ghati", "Mobile Num": "8962153561", "Acct Opn Date": 45335.0, "Sanct Lim Amount": 20000.0, "O/S Bal": -9236.35, "Os In Dr": 9236.35, "Uri": 116.0, "Os-Uri In Dr": 9120.35, "Scheme Code": "LA706", "CIF NPA date": 45779.0, "Asset Code 30.09.25": 21.0, "Days": 46008.0, "UCI": 386.2405756849315, "Secured": 9120.35, "Un Secured": 0.0, "Provision": 912.0350000000001, "Remarks": null}, "33035110000200": {"Acct Number": 33035110000200.0, "Sol": 3300.0, "Region": "Sehore", "Branch": "Rajgarh", "Cust Id": 382779.0, "Acct Name": "Biram Singh So Hari Singh", "Comm Add 1": "Ghataikheda", "Mobile Num": "9770827821", "Acct Opn Date": 41255.0, "Sanct Lim Amount": 55000.0, "O/S Bal": -10213.82, "Os In Dr": 10213.82, "Uri": 363.87, "Os-Uri In Dr": 9849.949999999999, "Scheme Code": "CC351", "CIF NPA date": 45378.0, "Asset Code 30.09.25": 31.0, "Days": 46008.0, "UCI": 1147.5866404109588, "Secured": 9849.949999999999, "Un Secured": 0.0, "Provision": 1969.9899999999998, "Remarks": null}, "33075510000103": {"Acct Number": 33075510000103.0, "Sol": 3300.0, "Region": "Sehore", "Branch": "Rajgarh", "Cust Id": 2148975.0, "Acct Name": "Kalusingh S/O Ramkishan Kumahar", "Comm Add 1": "Gram-Piplbey Post Hirankhedi", "Mobile Num": "9584365886", "Acct Opn Date": 42405.0, "Sanct Lim Amount": 100000.0, "O/S Bal": -28811.18, "Os In Dr": 28811.18, "Uri": 780.0, "Os-Uri In Dr": 28031.18, "Scheme Code": "LA755", "CIF NPA date": 45929.0, "Asset Code 30.09.25": 21.0, "Days": 46008.0, "UCI": 409.5240201369863, "Secured": 28031.18, "Un Secured": 0.0, "Provision": 2803.1180000000004, "Remarks": null}, "33075510000112": {"Acct Number": 33075510000112.0, "Sol": 3300.0, "Region": "Sehore", "Branch": "Rajgarh", "Cust Id": 2165500.0, "Acct Name": "Badrilal S/O Mog Ji Sondhya", "Comm Add 1": "Gram-Piplbey Post Hirankhedi", "Mobile Num": "7372255099", "Acct Opn Date": 42488.0, "Sanct Lim Amount": 100000.0, "O/S Bal": -31545.14, "Os In Dr": 31545.14, "Uri": 790.0, "Os-Uri In Dr": 30755.14, "Scheme Code": "LA755", "CIF NPA date": 45899.0, "Asset Code 30.09.25": 21.0, "Days": 46008.0, "UCI": 619.9477878082191, "Secured": 30755.14, "Un Secured": 0.0, "Provision": 3075.514, "Remarks": null}, "33075510000118": {"Acct Number": 33075510000118.0, "Sol": 3300.0, "Region": "Sehore", "Branch": "Rajgarh", "Cust Id": 2293831.0, "Acct Name": "Gordhan S/O Mangilal", "Comm Add 1": "Village-Daftari Ki Bavdi Post Hirankhedi", "Mobile Num": "9617616033", "Acct Opn Date": 42726.0, "Sanct Lim Amount": 100000.0, "O/S Bal": -47035.5, "Os In Dr": 47035.5, "Uri": 0.0, "Os-Uri In Dr": 47035.5, "Scheme Code": "LA755", "CIF NPA date": 44862.0, "Asset Code 30.09.25": 32.0, "Days": 46008.0, "UCI": 9968.304390410958, "Secured": 35000.0, "Un Secured": 12035.5, "Provision": 22535.5, "Remarks": null}, "33070610000073": {"Acct Number": 33070610000073.0, "Sol": 3300.0, "Region": "Sehore", "Branch": "Rajgarh", "Cust Id": 2358279.0, "Acct Name": "Mohsin Gauri S/O Abdul Gaffar", "Comm Add 1": "Birjipura Old Collectret Road Rajgarh", "Mobile Num": "8770092597", "Acct Opn Date": 44520.0, "Sanct Lim Amount": 20000.0, "O/S Bal": -12669.61, "Os In Dr": 12669.61, "Uri": 0.0, "Os-Uri In Dr": 12669.61, "Scheme Code": "LA706", "CIF NPA date": 44681.0, "Asset Code 30.09.25": 40.0, "Days": 46008.0, "UCI": 3109.174360890411, "Secured": 0.0, "Un Secured": 12669.61, "Provision": 12669.61, "Remarks": null}, "33075510000111": {"Acct Number": 33075510000111.0, "Sol": 3300.0, "Region": "Sehore", "Branch": "Rajgarh", "Cust Id": 2364566.0, "Acct Name": "Rambabu Tanwar S/O Nagaji Tanwar", "Comm Add 1": "Gram- Bhawanipura ,Post -Hirankhedi", "Mobile Num": "9981793987", "Acct Opn Date": 42487.0, "Sanct Lim Amount": 100000.0, "O/S Bal": -32472.9, "Os In Dr": 32472.9, "Uri": 554.0, "Os-Uri In Dr": 31918.9, "Scheme Code": "LA755", "CIF NPA date": 45868.0, "Asset Code 30.09.25": 21.0, "Days": 46008.0, "UCI": 826.3934383561644, "Secured": 31918.9, "Un Secured": 0.0, "Provision": 3191.8900000000003, "Remarks": null}, "33070610000070": {"Acct Number": 33070610000070.0, "Sol": 3300.0, "Region": "Sehore", "Branch": "Rajgarh", "Cust Id": 2575238.0, "Acct Name": "Dinesh S/O Rodji Vanshkar", "Comm Add 1": "Ward1", "Mobile Num": "9926176019", "Acct Opn Date": 44499.0, "Sanct Lim Amount": 10000.0, "O/S Bal": -4719.0, "Os In Dr": 4719.0, "Uri": 0.0, "Os-Uri In Dr": 4719.0, "Scheme Code": "LA706", "CIF NPA date": 44681.0, "Asset Code 30.09.25": 40.0, "Days": 46008.0, "UCI": 1158.0619931506849, "Secured": 0.0, "Un Secured": 4719.0, "Provision": 4719.0, "Remarks": null}, "33070610000068": {"Acct Number": 33070610000068.0, "Sol": 3300.0, "Region": "Sehore", "Branch": "Rajgarh", "Cust Id": 2575249.0, "Acct Name": "Ashok S/O Rodji", "Comm Add 1": "Ward No 1 Khoyari Road", "Mobile Num": "7746882016", "Acct Opn Date": 44499.0, "Sanct Lim Amount": 10000.0, "O/S Bal": -5989.0, "Os In Dr": 5989.0, "Uri": 0.0, "Os-Uri In Dr": 5989.0, "Scheme Code": "LA706", "CIF NPA date": 44709.0, "Asset Code 30.09.25": 40.0, "Days": 46008.0, "UCI": 1438.7136780821918, "Secured": 0.0, "Un Secured": 5989.0, "Provision": 5989.0, "Remarks": null}, "33070610000061": {"Acct Number": 33070610000061.0, "Sol": 3300.0, "Region": "Sehore", "Branch": "Rajgarh", "Cust Id": 2575251.0, "Acct Name": "Suresh S/O Vanshilal Bhilala", "Comm Add 1": "Ward No 1 Khoyari Road", "Mobile Num": "7000804169", "Acct Opn Date": 44456.0, "Sanct Lim Amount": 10000.0, "O/S Bal": -9083.49, "Os In Dr": 9083.49, "Uri": 178.97, "Os-Uri In Dr": 8904.52, "Scheme Code": "LA706", "CIF NPA date": 44650.0, "Asset Code 30.09.25": 40.0, "Days": 46008.0, "UCI": 2236.254317260274, "Secured": 0.0, "Un Secured": 8904.52, "Provision": 8904.52, "Remarks": null}, "33073410000033": {"Acct Number": 33073410000033.0, "Sol": 3300.0, "Region": "Sehore", "Branch": "Rajgarh", "Cust Id": 2575260.0, "Acct Name": "Sanjay Basodiya So Ramesh Basodiya", "Comm Add 1": "Ward No 1 Khoyari Road", "Mobile Num": "7354379149", "Acct Opn Date": 43763.0, "Sanct Lim Amount": 180000.0, "O/S Bal": -65734.15, "Os In Dr": 65734.15, "Uri": 2507.0, "Os-Uri In Dr": 63227.149999999994, "Scheme Code": "LA734", "CIF NPA date": 45046.0, "Asset Code 30.09.25": 40.0, "Days": 46008.0, "UCI": 11248.369822602739, "Secured": 0.0, "Un Secured": 63227.149999999994, "Provision": 63227.149999999994, "Remarks": null}, "33070610000065": {"Acct Number": 33070610000065.0, "Sol": 3300.0, "Region": "Sehore", "Branch": "Rajgarh", "Cust Id": 2597700.0, "Acct Name": "Lakhan S/O Ramesh Chandra Mehar", "Comm Add 1": "Ward No-1 Khoyari Road Rajgarh", "Mobile Num": "8120151926", "Acct Opn Date": 44475.0, "Sanct Lim Amount": 10000.0, "O/S Bal": -4724.75, "Os In Dr": 4724.75, "Uri": 0.0, "Os-Uri In Dr": 4724.75, "Scheme Code": "LA706", "CIF NPA date": 44770.0, "Asset Code 30.09.25": 40.0, "Days": 46008.0, "UCI": 1081.7088595890411, "Secured": 0.0, "Un Secured": 4724.75, "Provision": 4724.75, "Remarks": null}, "33070810000017": {"Acct Number": 33070810000017.0, "Sol": 3300.0, "Region": "Sehore", "Branch": "Rajgarh", "Cust Id": 2747823.0, "Acct Name": "Pappusingh S/O Chainsingh Tawar", "Comm Add 1": "Titodi Po Pipalbe", "Mobile Num": "9165923941", "Acct Opn Date": 44223.0, "Sanct Lim Amount": 10000.0, "O/S Bal": -8052.0, "Os In Dr": 8052.0, "Uri": 0.0, "Os-Uri In Dr": 8052.0, "Scheme Code": "LA708", "CIF NPA date": 44497.0, "Asset Code 30.09.25": 40.0, "Days": 46008.0, "UCI": 2249.982493150685, "Secured": 0.0, "Un Secured": 8052.0, "Provision": 8052.0, "Remarks": null}, "33075510000113": {"Acct Number": 33075510000113.0, "Sol": 3300.0, "Region": "Sehore", "Branch": "Rajgarh", "Cust Id": 2975709.0, "Acct Name": "Mangibai W/O Paremsingh Tanwar", "Comm Add 1": "Village-Hirankhedi,Panchayat-Pipalbehpuro", "Mobile Num": "9174458230", "Acct Opn Date": 42500.0, "Sanct Lim Amount": 100000.0, "O/S Bal": -21539.0, "Os In Dr": 21539.0, "Uri": 0.0, "Os-Uri In Dr": 21539.0, "Scheme Code": "LA755", "CIF NPA date": 43523.0, "Asset Code 30.09.25": 33.0, "Days": 46008.0, "UCI": 9898.350719178083, "Secured": 21539.0, "Un Secured": 0.0, "Provision": 21539.0, "Remarks": null}, "33070810000010": {"Acct Number": 33070810000010.0, "Sol": 3300.0, "Region": "Sehore", "Branch": "Rajgarh", "Cust Id": 3041549.0, "Acct Name": "Mangilal Tanwar So Ramchandar Tanwar", "Comm Add 1": "Gram Hirenkhedi", "Mobile Num": "7806050054", "Acct Opn Date": 44184.0, "Sanct Lim Amount": 10000.0, "O/S Bal": -7615.0, "Os In Dr": 7615.0, "Uri": 0.0, "Os-Uri In Dr": 7615.0, "Scheme Code": "LA708", "CIF NPA date": 44286.0, "Asset Code 30.09.25": 40.0, "Days": 46008.0, "UCI": 2425.012397260274, "Secured": 0.0, "Un Secured": 7615.0, "Provision": 7615.0, "Remarks": null}, "33070810000027": {"Acct Number": 33070810000027.0, "Sol": 3300.0, "Region": "Sehore", "Branch": "Rajgarh", "Cust Id": 3058447.0, "Acct Name": "Rakesh So Shambhulal Verma", "Comm Add 1": "Village-Hirankhedi,Panchayat-Pipalbehpuro", "Mobile Num": "8878186241", "Acct Opn Date": 44530.0, "Sanct Lim Amount": 10000.0, "O/S Bal": -8420.0, "Os In Dr": 8420.0, "Uri": 0.0, "Os-Uri In Dr": 8420.0, "Scheme Code": "LA708", "CIF NPA date": 44770.0, "Asset Code 30.09.25": 40.0, "Days": 46008.0, "UCI": 1927.7186301369863, "Secured": 0.0, "Un Secured": 8420.0, "Provision": 8420.0, "Remarks": null}, "33075510000065": {"Acct Number": 33075510000065.0, "Sol": 3300.0, "Region": "Sehore", "Branch": "Rajgarh", "Cust Id": 3252100.0, "Acct Name": "Sardarsingh S/O Jagnnath, Shantibai W/O Sardarsingh", "Comm Add 1": "Village-Dapatarikibavd,Panchayat-Kalikheda", "Mobile Num": "8966941339", "Acct Opn Date": 41752.0, "Sanct Lim Amount": 100000.0, "O/S Bal": -7109.06, "Os In Dr": 7109.06, "Uri": 1756.06, "Os-Uri In Dr": 5353.0, "Scheme Code": "LA755", "CIF NPA date": 45929.0, "Asset Code 30.09.25": 21.0, "Days": 46008.0, "UCI": 78.2051301369863, "Secured": 5353.0, "Un Secured": 0.0, "Provision": 535.3000000000001, "Remarks": null}, "33070810000026": {"Acct Number": 33070810000026.0, "Sol": 3300.0, "Region": "Sehore", "Branch": "Rajgarh", "Cust Id": 3313628.0, "Acct Name": "Ramprasad S/O Ghisalal Tanwar", "Comm Add 1": "Village-Dapatarikibavd,Panchayat-Kalikheda", "Mobile Num": "9691929059", "Acct Opn Date": 44526.0, "Sanct Lim Amount": 10000.0, "O/S Bal": -1979.6, "Os In Dr": 1979.6, "Uri": 0.0, "Os-Uri In Dr": 1979.6, "Scheme Code": "LA708", "CIF NPA date": 45015.0, "Asset Code 30.09.25": 40.0, "Days": 46008.0, "UCI": 363.52777808219173, "Secured": 0.0, "Un Secured": 1979.6, "Provision": 1979.6, "Remarks": null}, "33070610000117": {"Acct Number": 33070610000117.0, "Sol": 3300.0, "Region": "Sehore", "Branch": "Rajgarh", "Cust Id": 3376890.0, "Acct Name": "Ramprasad S/O Gordhan Tanwar", "Comm Add 1": "Vill Nalkheda", "Mobile Num": "9171723249", "Acct Opn Date": 45097.0, "Sanct Lim Amount": 20000.0, "O/S Bal": -4038.91, "Os In Dr": 4038.91, "Uri": 0.0, "Os-Uri In Dr": 4038.91, "Scheme Code": "LA706", "CIF NPA date": 45595.0, "Asset Code 30.09.25": 40.0, "Days": 46008.0, "UCI": 308.4786671917808, "Secured": 0.0, "Un Secured": 4038.91, "Provision": 4038.91, "Remarks": null}, "33030110000167": {"Acct Number": 33030110000167.0, "Sol": 3300.0, "Region": "Sehore", "Branch": "Rajgarh", "Cust Id": 3396407.0, "Acct Name": "Rajesh So Dariyav Singh Tanwar", "Comm Add 1": "Hirankhedi Post Pipalway Purohit", "Mobile Num": "9302094994", "Acct Opn Date": 45132.0, "Sanct Lim Amount": 50000.0, "O/S Bal": -52329.7, "Os In Dr": 52329.7, "Uri": 1128.0, "Os-Uri In Dr": 51201.7, "Scheme Code": "CC301", "CIF NPA date": 45554.0, "Asset Code 30.09.25": 40.0, "Days": 46008.0, "UCI": 4298.838620547945, "Secured": 0.0, "Un Secured": 51201.7, "Provision": 51201.7, "Remarks": null}, "33070610000066": {"Acct Number": 33070610000066.0, "Sol": 3300.0, "Region": "Sehore", "Branch": "Rajgarh", "Cust Id": 3409917.0, "Acct Name": "Dinesh S/O Banshilal Bhilala", "Comm Add 1": "Ward No.01 Rajgarh,Khoyri Road Rajgarh", "Mobile Num": "7803090057", "Acct Opn Date": 44475.0, "Sanct Lim Amount": 10000.0, "O/S Bal": -8105.84, "Os In Dr": 8105.84, "Uri": 0.0, "Os-Uri In Dr": 8105.84, "Scheme Code": "LA706", "CIF NPA date": 44681.0, "Asset Code 30.09.25": 40.0, "Days": 46008.0, "UCI": 1989.206447671233, "Secured": 0.0, "Un Secured": 8105.84, "Provision": 8105.84, "Remarks": null}, "33070810000030": {"Acct Number": 33070810000030.0, "Sol": 3300.0, "Region": "Sehore", "Branch": "Rajgarh", "Cust Id": 3817333.0, "Acct Name": "Gokal So Deviram", "Comm Add 1": "Village-Na,Panchayat-Hirankhedi", "Mobile Num": "9516717864", "Acct Opn Date": 44530.0, "Sanct Lim Amount": 10000.0, "O/S Bal": -7222.0, "Os In Dr": 7222.0, "Uri": 0.0, "Os-Uri In Dr": 7222.0, "Scheme Code": "LA708", "CIF NPA date": 44831.0, "Asset Code 30.09.25": 40.0, "Days": 46008.0, "UCI": 1571.9721780821917, "Secured": 0.0, "Un Secured": 7222.0, "Provision": 7222.0, "Remarks": null}, "33070810000028": {"Acct Number": 33070810000028.0, "Sol": 3300.0, "Region": "Sehore", "Branch": "Rajgarh", "Cust Id": 4315806.0, "Acct Name": "Biram So Ramesh", "Comm Add 1": "Gram Hirenkhedi Post Pipalbey", "Mobile Num": "9516677394", "Acct Opn Date": 44530.0, "Sanct Lim Amount": 10000.0, "O/S Bal": -10338.6, "Os In Dr": 10338.6, "Uri": 238.6, "Os-Uri In Dr": 10100.0, "Scheme Code": "LA708", "CIF NPA date": 44681.0, "Asset Code 30.09.25": 40.0, "Days": 46008.0, "UCI": 2478.5815068493152, "Secured": 0.0, "Un Secured": 10100.0, "Provision": 10100.0, "Remarks": null}, "33065710000105": {"Acct Number": 33065710000105.0, "Sol": 3300.0, "Region": "Sehore", "Branch": "Rajgarh", "Cust Id": 4571484.0, "Acct Name": "Guddi Bai", "Comm Add 1": "19 Koyri Road,Rajgarh", "Mobile Num": "9009448175", "Acct Opn Date": 44469.0, "Sanct Lim Amount": 7900.0, "O/S Bal": -7900.0, "Os In Dr": 7900.0, "Uri": 0.0, "Os-Uri In Dr": 7900.0, "Scheme Code": "LA657", "CIF NPA date": 44681.0, "Asset Code 30.09.25": 40.0, "Days": 46008.0, "UCI": 1938.6924657534246, "Secured": 0.0, "Un Secured": 7900.0, "Provision": 7900.0, "Remarks": null}, "33070610000037": {"Acct Number": 33070610000037.0, "Sol": 3300.0, "Region": "Sehore", "Branch": "Rajgarh", "Cust Id": 4571484.0, "Acct Name": "Guddi Bai Wo Kallu", "Comm Add 1": "19 Koyri Road,Rajgarh", "Mobile Num": "9009448175", "Acct Opn Date": 44237.0, "Sanct Lim Amount": 10000.0, "O/S Bal": -2446.27, "Os In Dr": 2446.27, "Uri": 47.15, "Os-Uri In Dr": 2399.12, "Scheme Code": "LA706", "CIF NPA date": 44681.0, "Asset Code 30.09.25": 40.0, "Days": 46008.0, "UCI": 588.7539073972603, "Secured": 0.0, "Un Secured": 2399.12, "Provision": 2399.12, "Remarks": null}, "33070610000136": {"Acct Number": 33070610000136.0, "Sol": 3300.0, "Region": "Sehore", "Branch": "Rajgarh", "Cust Id": 4597840.0, "Acct Name": "Prmila Bai Wo Maheshkumar Prajapati", "Comm Add 1": "Ward No11 Gali No 05 Tilak Marg", "Mobile Num": "8827714633", "Acct Opn Date": 45335.0, "Sanct Lim Amount": 20000.0, "O/S Bal": -2672.91, "Os In Dr": 2672.91, "Uri": 65.0, "Os-Uri In Dr": 2607.91, "Scheme Code": "LA706", "CIF NPA date": 45929.0, "Asset Code 30.09.25": 21.0, "Days": 46008.0, "UCI": 38.10049335616438, "Secured": 2607.91, "Un Secured": 0.0, "Provision": 260.791, "Remarks": null}, "33070610000069": {"Acct Number": 33070610000069.0, "Sol": 3300.0, "Region": "Sehore", "Branch": "Rajgarh", "Cust Id": 100878469.0, "Acct Name": "Urmila Bai", "Comm Add 1": "Ward N.03,Kaala Khet", "Mobile Num": "6267144589", "Acct Opn Date": 44499.0, "Sanct Lim Amount": 10000.0, "O/S Bal": -10144.71, "Os In Dr": 10144.71, "Uri": 232.71, "Os-Uri In Dr": 9912.0, "Scheme Code": "LA706", "CIF NPA date": 44681.0, "Asset Code 30.09.25": 40.0, "Days": 46008.0, "UCI": 2432.4455342465753, "Secured": 0.0, "Un Secured": 9912.0, "Provision": 9912.0, "Remarks": null}, "33070610000094": {"Acct Number": 33070610000094.0, "Sol": 3300.0, "Region": "Sehore", "Branch": "Rajgarh", "Cust Id": 100907515.0, "Acct Name": "Babu Lal So Shivnarayan", "Comm Add 1": "House 02 Gali 04 Ward 03 Pura Rajgarh", "Mobile Num": "8964849035", "Acct Opn Date": 44865.0, "Sanct Lim Amount": 50000.0, "O/S Bal": -13261.55, "Os In Dr": 13261.55, "Uri": 476.0, "Os-Uri In Dr": 12785.55, "Scheme Code": "LA706", "CIF NPA date": 45838.0, "Asset Code 30.09.25": 21.0, "Days": 46008.0, "UCI": 401.9566746575342, "Secured": 12785.55, "Un Secured": 0.0, "Provision": 1278.555, "Remarks": null}, "33070610000082": {"Acct Number": 33070610000082.0, "Sol": 3300.0, "Region": "Sehore", "Branch": "Rajgarh", "Cust Id": 101039642.0, "Acct Name": "Mohan Kala Bai Wo Jaynarayan", "Comm Add 1": "Sankat Mochan Rajgarh", "Mobile Num": "9171723448", "Acct Opn Date": 44574.0, "Sanct Lim Amount": 10000.0, "O/S Bal": -4522.99, "Os In Dr": 4522.99, "Uri": 0.0, "Os-Uri In Dr": 4522.99, "Scheme Code": "LA706", "CIF NPA date": 44801.0, "Asset Code 30.09.25": 40.0, "Days": 46008.0, "UCI": 1009.5871308904109, "Secured": 0.0, "Un Secured": 4522.99, "Provision": 4522.99, "Remarks": null}, "33070610000064": {"Acct Number": 33070610000064.0, "Sol": 3300.0, "Region": "Sehore", "Branch": "Rajgarh", "Cust Id": 101108433.0, "Acct Name": "Mahesh", "Comm Add 1": "Rajgarh,Khoyari Road Rajgarh,R", "Mobile Num": "8103108933", "Acct Opn Date": 44475.0, "Sanct Lim Amount": 10000.0, "O/S Bal": -10190.66, "Os In Dr": 10190.66, "Uri": 204.15, "Os-Uri In Dr": 9986.51, "Scheme Code": "LA706", "CIF NPA date": 44650.0, "Asset Code 30.09.25": 40.0, "Days": 46008.0, "UCI": 2507.9820250684934, "Secured": 0.0, "Un Secured": 9986.51, "Provision": 9986.51, "Remarks": null}, "33070610000050": {"Acct Number": 33070610000050.0, "Sol": 3300.0, "Region": "Sehore", "Branch": "Rajgarh", "Cust Id": 101207987.0, "Acct Name": "Sunita Verma Wo Rajaram Verma", "Comm Add 1": "105/2,Rajgarh,Baradvari Nale Ki Jhop", "Mobile Num": "6264430037", "Acct Opn Date": 44407.0, "Sanct Lim Amount": 10000.0, "O/S Bal": -2953.58, "Os In Dr": 2953.58, "Uri": 0.0, "Os-Uri In Dr": 2953.58, "Scheme Code": "LA706", "CIF NPA date": 44709.0, "Asset Code 30.09.25": 40.0, "Days": 46008.0, "UCI": 709.52679, "Secured": 0.0, "Un Secured": 2953.58, "Provision": 2953.58, "Remarks": null}, "33070610000054": {"Acct Number": 33070610000054.0, "Sol": 3300.0, "Region": "Sehore", "Branch": "Rajgarh", "Cust Id": 101228654.0, "Acct Name": "Hukam Chand S/O Amar Lal", "Comm Add 1": "Ward N. 03,Kumhaar Mohalla Pura R", "Mobile Num": "8717913524", "Acct Opn Date": 44424.0, "Sanct Lim Amount": 10000.0, "O/S Bal": -9185.0, "Os In Dr": 9185.0, "Uri": 245.81, "Os-Uri In Dr": 8939.19, "Scheme Code": "LA706", "CIF NPA date": 44619.0, "Asset Code 30.09.25": 40.0, "Days": 46008.0, "UCI": 2296.2085107534244, "Secured": 0.0, "Un Secured": 8939.19, "Provision": 8939.19, "Remarks": null}, "33070610000127": {"Acct Number": 33070610000127.0, "Sol": 3300.0, "Region": "Sehore", "Branch": "Rajgarh", "Cust Id": 101289165.0, "Acct Name": "Ikram Shah So Ibrahim Shah", "Comm Add 1": "Ward N. 04,Kaala Khet Hanuman Man", "Mobile Num": "6264295997", "Acct Opn Date": 45217.0, "Sanct Lim Amount": 10000.0, "O/S Bal": -3357.22, "Os In Dr": 3357.22, "Uri": 82.0, "Os-Uri In Dr": 3275.22, "Scheme Code": "LA706", "CIF NPA date": 45626.0, "Asset Code 30.09.25": 40.0, "Days": 46008.0, "UCI": 231.37410328767123, "Secured": 0.0, "Un Secured": 3275.22, "Provision": 3275.22, "Remarks": null}, "33070810000031": {"Acct Number": 33070810000031.0, "Sol": 3300.0, "Region": "Sehore", "Branch": "Rajgarh", "Cust Id": 101379023.0, "Acct Name": "Gajraj Singh So Kesar Singh", "Comm Add 1": "H No 02 Gram Uchakheda Post Hirenkhedi", "Mobile Num": "8718987287", "Acct Opn Date": 44576.0, "Sanct Lim Amount": 10000.0, "O/S Bal": -3194.84, "Os In Dr": 3194.84, "Uri": 0.0, "Os-Uri In Dr": 3194.84, "Scheme Code": "LA708", "CIF NPA date": 44862.0, "Asset Code 30.09.25": 40.0, "Days": 46008.0, "UCI": 677.0872553424658, "Secured": 0.0, "Un Secured": 3194.84, "Provision": 3194.84, "Remarks": null}, "33070610000124": {"Acct Number": 33070610000124.0, "Sol": 3300.0, "Region": "Sehore", "Branch": "Rajgarh", "Cust Id": 101453117.0, "Acct Name": "Manoj Rana So Mohan Lal Rana", "Comm Add 1": "Vikram Marg Gali No. 2", "Mobile Num": "7089441012", "Acct Opn Date": 45166.0, "Sanct Lim Amount": 20000.0, "O/S Bal": -17285.58, "Os In Dr": 17285.58, "Uri": 450.0, "Os-Uri In Dr": 16835.58, "Scheme Code": "LA706", "CIF NPA date": 45381.0, "Asset Code 30.09.25": 40.0, "Days": 46008.0, "UCI": 1952.1200946575343, "Secured": 0.0, "Un Secured": 16835.58, "Provision": 16835.58, "Remarks": null}, "33070610000014": {"Acct Number": 33070610000014.0, "Sol": 3300.0, "Region": "Sehore", "Branch": "Rajgarh", "Cust Id": 101483133.0, "Acct Name": "Tulsi So Amarchand", "Comm Add 1": "Ward 3 Pura Rajgarh", "Mobile Num": "8269945862", "Acct Opn Date": 44081.0, "Sanct Lim Amount": 10000.0, "O/S Bal": -10215.02, "Os In Dr": 10215.02, "Uri": 436.0, "Os-Uri In Dr": 9779.02, "Scheme Code": "LA706", "CIF NPA date": 44254.0, "Asset Code 30.09.25": 40.0, "Days": 46008.0, "UCI": 3172.01937780822, "Secured": 0.0, "Un Secured": 9779.02, "Provision": 9779.02, "Remarks": null}, "33070610000092": {"Acct Number": 33070610000092.0, "Sol": 3300.0, "Region": "Sehore", "Branch": "Rajgarh", "Cust Id": 101483189.0, "Acct Name": "Akil So Sattar", "Comm Add 1": "Ward 03 Kumhar Mohalla", "Mobile Num": "7909719513", "Acct Opn Date": 44848.0, "Sanct Lim Amount": 50000.0, "O/S Bal": -48766.03, "Os In Dr": 48766.03, "Uri": 613.25, "Os-Uri In Dr": 48152.78, "Scheme Code": "LA706", "CIF NPA date": 44999.0, "Asset Code 30.09.25": 40.0, "Days": 46008.0, "UCI": 8985.110859863013, "Secured": 4000.0, "Un Secured": 44152.78, "Provision": 48152.78, "Remarks": null}, "33070610000011": {"Acct Number": 33070610000011.0, "Sol": 3300.0, "Region": "Sehore", "Branch": "Rajgarh", "Cust Id": 101483252.0, "Acct Name": "Nilesh Sahu Wo Ganesh Sahu", "Comm Add 1": "Topkhana Rajgarh", "Mobile Num": "9174381436", "Acct Opn Date": 44081.0, "Sanct Lim Amount": 10000.0, "O/S Bal": -863.63, "Os In Dr": 863.63, "Uri": 28.0, "Os-Uri In Dr": 835.63, "Scheme Code": "LA706", "CIF NPA date": 44497.0, "Asset Code 30.09.25": 40.0, "Days": 46008.0, "UCI": 233.50135006849314, "Secured": 0.0, "Un Secured": 835.63, "Provision": 835.63, "Remarks": null}, "33070610000030": {"Acct Number": 33070610000030.0, "Sol": 3300.0, "Region": "Sehore", "Branch": "Rajgarh", "Cust Id": 101562175.0, "Acct Name": "Narsingh Pahadiya So Hari Prasad Pahadiya", "Comm Add 1": "Ward N.03,Kumahar Mohalla Pura", "Mobile Num": "9709169336", "Acct Opn Date": 44140.0, "Sanct Lim Amount": 10000.0, "O/S Bal": -4496.28, "Os In Dr": 4496.28, "Uri": 0.0, "Os-Uri In Dr": 4496.28, "Scheme Code": "LA706", "CIF NPA date": 44286.0, "Asset Code 30.09.25": 40.0, "Days": 46008.0, "UCI": 1431.8496049315067, "Secured": 0.0, "Un Secured": 4496.28, "Provision": 4496.28, "Remarks": null}, "33070810000016": {"Acct Number": 33070810000016.0, "Sol": 3300.0, "Region": "Sehore", "Branch": "Rajgarh", "Cust Id": 101709648.0, "Acct Name": "Surendra Singh", "Comm Add 1": "Village-Na,Panchayat-Kalikheda", "Mobile Num": "9977077556", "Acct Opn Date": 44221.0, "Sanct Lim Amount": 10000.0, "O/S Bal": -7129.0, "Os In Dr": 7129.0, "Uri": 0.0, "Os-Uri In Dr": 7129.0, "Scheme Code": "LA708", "CIF NPA date": 44528.0, "Asset Code 30.09.25": 40.0, "Days": 46008.0, "UCI": 1951.1975342465753, "Secured": 7000.0, "Un Secured": 129.0, "Provision": 7129.0, "Remarks": null}, "33070610000056": {"Acct Number": 33070610000056.0, "Sol": 3300.0, "Region": "Sehore", "Branch": "Rajgarh", "Cust Id": 101948300.0, "Acct Name": "Kapil Sen So Harinarayan Sen", "Comm Add 1": "Ward 11,Purani Tahsil Ke Piche", "Mobile Num": "7345686960", "Acct Opn Date": 44424.0, "Sanct Lim Amount": 10000.0, "O/S Bal": -9978.14, "Os In Dr": 9978.14, "Uri": 187.64, "Os-Uri In Dr": 9790.5, "Scheme Code": "LA706", "CIF NPA date": 44589.0, "Asset Code 30.09.25": 40.0, "Days": 46008.0, "UCI": 2569.201551369863, "Secured": 0.0, "Un Secured": 9790.5, "Provision": 9790.5, "Remarks": null}, "33073410000070": {"Acct Number": 33073410000070.0, "Sol": 3300.0, "Region": "Sehore", "Branch": "Rajgarh", "Cust Id": 102074437.0, "Acct Name": "Manju Bai Wo Lakhan Sen", "Comm Add 1": "Jhuggi Jhopdi Bypass Sankat Mochan Colony", "Mobile Num": "8120653983", "Acct Opn Date": 44939.0, "Sanct Lim Amount": 50000.0, "O/S Bal": -35522.42, "Os In Dr": 35522.42, "Uri": 1075.0, "Os-Uri In Dr": 34447.42, "Scheme Code": "LA734", "CIF NPA date": 45807.0, "Asset Code 30.09.25": 21.0, "Days": 46008.0, "UCI": 1280.453070821918, "Secured": 34447.42, "Un Secured": 0.0, "Provision": 3444.742, "Remarks": null}, "33070610000077": {"Acct Number": 33070610000077.0, "Sol": 3300.0, "Region": "Sehore", "Branch": "Rajgarh", "Cust Id": 102154954.0, "Acct Name": "Ravi Mewade So Kelash Narayan Mewade", "Comm Add 1": "Ward No 6 Tilak Marg Rajgarh", "Mobile Num": "9713191225", "Acct Opn Date": 44550.0, "Sanct Lim Amount": 10000.0, "O/S Bal": -7997.43, "Os In Dr": 7997.43, "Uri": 92.76, "Os-Uri In Dr": 7904.67, "Scheme Code": "LA706", "CIF NPA date": 44770.0, "Asset Code 30.09.25": 40.0, "Days": 46008.0, "UCI": 1809.7362973972602, "Secured": 0.0, "Un Secured": 7904.67, "Provision": 7904.67, "Remarks": null}, "33073410000050": {"Acct Number": 33073410000050.0, "Sol": 3300.0, "Region": "Sehore", "Branch": "Rajgarh", "Cust Id": 102599411.0, "Acct Name": "Jigar Kirana Store", "Comm Add 1": "95 Sankat Mochan Rajgarh", "Mobile Num": "9999999999", "Acct Opn Date": 44799.0, "Sanct Lim Amount": 500000.0, "O/S Bal": -300628.46, "Os In Dr": 300628.46, "Uri": 6563.0, "Os-Uri In Dr": 294065.46, "Scheme Code": "LA734", "CIF NPA date": 45868.0, "Asset Code 30.09.25": 21.0, "Days": 46008.0, "UCI": 7613.47560821918, "Secured": 294065.46, "Un Secured": 0.0, "Provision": 29406.546000000002, "Remarks": null}, "33073410000055": {"Acct Number": 33073410000055.0, "Sol": 3300.0, "Region": "Sehore", "Branch": "Rajgarh", "Cust Id": 102682225.0, "Acct Name": "Mahakal Kirana Store", "Comm Add 1": "Village Bhawni Pura", "Mobile Num": "8120670938", "Acct Opn Date": 44834.0, "Sanct Lim Amount": 300000.0, "O/S Bal": -190535.3, "Os In Dr": 190535.3, "Uri": 6147.3, "Os-Uri In Dr": 184388.0, "Scheme Code": "LA734", "CIF NPA date": 45838.0, "Asset Code 30.09.25": 21.0, "Days": 46008.0, "UCI": 5796.855616438356, "Secured": 184388.0, "Un Secured": 0.0, "Provision": 18438.8, "Remarks": null}, "33035110000021": {"Acct Number": 33035110000021.0, "Sol": 3300.0, "Region": "Sehore", "Branch": "Rajgarh", "Cust Id": 999010145.0, "Acct Name": "Kalu Singh S/O Fateh Singh Sondhya", "Comm Add 1": "Village:--Manoharpura", "Mobile Num": "9174415481", "Acct Opn Date": 40458.0, "Sanct Lim Amount": 132000.0, "O/S Bal": -174229.65, "Os In Dr": 174229.65, "Uri": 32521.5, "Os-Uri In Dr": 141708.15, "Scheme Code": "CC351", "CIF NPA date": 45825.0, "Asset Code 30.09.25": 21.0, "Days": 46008.0, "UCI": 4795.753213356164, "Secured": 141708.15, "Un Secured": 0.0, "Provision": 14170.815, "Remarks": null}, "33075510000119": {"Acct Number": 33075510000119.0, "Sol": 3300.0, "Region": "Sehore", "Branch": "Rajgarh", "Cust Id": 999078796.0, "Acct Name": "Rambabu S/O Harisingh Sondhya", "Comm Add 1": "Village:-Khandiyapura Post:-Moya", "Mobile Num": "7354378248", "Acct Opn Date": 42770.0, "Sanct Lim Amount": 100000.0, "O/S Bal": -36135.16, "Os In Dr": 36135.16, "Uri": 0.0, "Os-Uri In Dr": 36135.16, "Scheme Code": "LA755", "CIF NPA date": 44650.0, "Asset Code 30.09.25": 32.0, "Days": 46008.0, "UCI": 9074.875181917809, "Secured": 27000.0, "Un Secured": 9135.160000000003, "Provision": 17235.160000000003, "Remarks": null}, "33076110000013": {"Acct Number": 33076110000013.0, "Sol": 3300.0, "Region": "Sehore", "Branch": "Rajgarh", "Cust Id": 999080475.0, "Acct Name": "Shrilal Jagannath So Ram Singh", "Comm Add 1": "Vilage Bhadvakheda Tehsil Rajgarh", "Mobile Num": "7372255099", "Acct Opn Date": 41634.0, "Sanct Lim Amount": 98515.0, "O/S Bal": -34698.9, "Os In Dr": 34698.9, "Uri": 0.0, "Os-Uri In Dr": 34698.9, "Scheme Code": "LA761", "CIF NPA date": 42460.0, "Asset Code 30.09.25": 40.0, "Days": 46008.0, "UCI": 22767.231673972605, "Secured": 0.0, "Un Secured": 34698.9, "Provision": 34698.9, "Remarks": null}, "33035110000110": {"Acct Number": 33035110000110.0, "Sol": 3300.0, "Region": "Sehore", "Branch": "Rajgarh", "Cust Id": 999080475.0, "Acct Name": "Shrilal Jagannath So Ram Singh", "Comm Add 1": "Vilage Bhadvakheda Tehsil Rajgarh", "Mobile Num": "7372255099", "Acct Opn Date": 40714.0, "Sanct Lim Amount": 85000.0, "O/S Bal": -30732.98, "Os In Dr": 30732.98, "Uri": 0.0, "Os-Uri In Dr": 30732.98, "Scheme Code": "CC351", "CIF NPA date": 42460.0, "Asset Code 30.09.25": 33.0, "Days": 46008.0, "UCI": 20165.044877260272, "Secured": 30732.98, "Un Secured": 0.0, "Provision": 30732.98, "Remarks": null}, "33075510000088": {"Acct Number": 33075510000088.0, "Sol": 3300.0, "Region": "Sehore", "Branch": "Rajgarh", "Cust Id": 999145257.0, "Acct Name": "Mangilal Tanwar S/O Champalal Tanwar", "Comm Add 1": "Village Hirankhedi Post Hirankhedi", "Mobile Num": "8435848544", "Acct Opn Date": 41941.0, "Sanct Lim Amount": 100000.0, "O/S Bal": 2318.72, "Os In Dr": 0.0, "Uri": 0.0, "Os-Uri In Dr": 0.0, "Scheme Code": "LA755", "CIF NPA date": 43735.0, "Asset Code 30.09.25": 33.0, "Days": 46008.0, "UCI": 0.0, "Secured": 0.0, "Un Secured": 0.0, "Provision": 0.0, "Remarks": null}, "33075510000014": {"Acct Number": 33075510000014.0, "Sol": 3300.0, "Region": "Sehore", "Branch": "Rajgarh", "Cust Id": 999414256.0, "Acct Name": "Papu Lal S/O Shri Chothmal Sharma & Mrs. Radha W/O Shri Papulal Sharma", "Comm Add 1": "Village Hirankhedi Post Hirankhedi", "Mobile Num": "9826336803", "Acct Opn Date": 41305.0, "Sanct Lim Amount": 60000.0, "O/S Bal": 252.64, "Os In Dr": 0.0, "Uri": 0.0, "Os-Uri In Dr": 0.0, "Scheme Code": "LA755", "CIF NPA date": 42793.0, "Asset Code 30.09.25": 33.0, "Days": 46008.0, "UCI": 0.0, "Secured": 0.0, "Un Secured": 0.0, "Provision": 0.0, "Remarks": null}, "33075510000005": {"Acct Number": 33075510000005.0, "Sol": 3300.0, "Region": "Sehore", "Branch": "Rajgarh", "Cust Id": 999414262.0, "Acct Name": "Madanlal S/O Shri Gangaram Tanwar & Mrs. Lalta Bai W/O Shri Madanlal Tanwar", "Comm Add 1": "Village Hirankhedi Post Hirankhedi", "Mobile Num": "9826336803", "Acct Opn Date": 41305.0, "Sanct Lim Amount": 60000.0, "O/S Bal": 0.0, "Os In Dr": 0.0, "Uri": 0.0, "Os-Uri In Dr": 0.0, "Scheme Code": "LA755", "CIF NPA date": 42640.0, "Asset Code 30.09.25": 33.0, "Days": 46008.0, "UCI": 0.0, "Secured": 0.0, "Un Secured": 0.0, "Provision": 0.0, "Remarks": null}, "33075510000018": {"Acct Number": 33075510000018.0, "Sol": 3300.0, "Region": "Sehore", "Branch": "Rajgarh", "Cust Id": 999414286.0, "Acct Name": "Beeram S/O Shri Jaganath Tanwar & Mrs. Mamta Bai W/O Beeram Tanwar", "Comm Add 1": "Village Hirankhedi Post Hirankhedi", "Mobile Num": "9826336803", "Acct Opn Date": 41305.0, "Sanct Lim Amount": 60000.0, "O/S Bal": 0.0, "Os In Dr": 0.0, "Uri": 0.0, "Os-Uri In Dr": 0.0, "Scheme Code": "LA755", "CIF NPA date": 42640.0, "Asset Code 30.09.25": 33.0, "Days": 46008.0, "UCI": 0.0, "Secured": 0.0, "Un Secured": 0.0, "Provision": 0.0, "Remarks": null}, "33075510000015": {"Acct Number": 33075510000015.0, "Sol": 3300.0, "Region": "Sehore", "Branch": "Rajgarh", "Cust Id": 999414305.0, "Acct Name": "Narayan Singh S/O Shri Navel Tanwar & Mrs. Kali Bai W/O Narayan Singh Tanwar", "Comm Add 1": "Village Hirankhedi Post Hirankhedi", "Mobile Num": "9826336803", "Acct Opn Date": 41305.0, "Sanct Lim Amount": 60000.0, "O/S Bal": 0.0, "Os In Dr": 0.0, "Uri": 0.0, "Os-Uri In Dr": 0.0, "Scheme Code": "LA755", "CIF NPA date": 42793.0, "Asset Code 30.09.25": 33.0, "Days": 46008.0, "UCI": 0.0, "Secured": 0.0, "Un Secured": 0.0, "Provision": 0.0, "Remarks": null}, "33075510000004": {"Acct Number": 33075510000004.0, "Sol": 3300.0, "Region": "Sehore", "Branch": "Rajgarh", "Cust Id": 999414314.0, "Acct Name": "Bapulal S/O Shri Girdhanri Lal Tanwar & Mrs Sorum Bai W/O Bapulal Tanwar", "Comm Add 1": "Village Hirankhedi Post Hirankhedi", "Mobile Num": "9826336803", "Acct Opn Date": 41305.0, "Sanct Lim Amount": 60000.0, "O/S Bal": 3002.38, "Os In Dr": 0.0, "Uri": 0.0, "Os-Uri In Dr": 0.0, "Scheme Code": "LA755", "CIF NPA date": 42824.0, "Asset Code 30.09.25": 33.0, "Days": 46008.0, "UCI": 0.0, "Secured": 0.0, "Un Secured": 0.0, "Provision": 0.0, "Remarks": null}, "33075510000020": {"Acct Number": 33075510000020.0, "Sol": 3300.0, "Region": "Sehore", "Branch": "Rajgarh", "Cust Id": 999414329.0, "Acct Name": "Devsingh Tanwar S/O Shri Ramsingh & Mrs. Dhishibai W/O Devsingh", "Comm Add 1": "Village Hirankhedi Post Hirankhedi", "Mobile Num": "9826336803", "Acct Opn Date": 41305.0, "Sanct Lim Amount": 60000.0, "O/S Bal": 18185.32, "Os In Dr": 0.0, "Uri": 0.0, "Os-Uri In Dr": 0.0, "Scheme Code": "LA755", "CIF NPA date": 43401.0, "Asset Code 30.09.25": 33.0, "Days": 46008.0, "UCI": 0.0, "Secured": 0.0, "Un Secured": 0.0, "Provision": 0.0, "Remarks": null}, "33075510000006": {"Acct Number": 33075510000006.0, "Sol": 3300.0, "Region": "Sehore", "Branch": "Rajgarh", "Cust Id": 999414331.0, "Acct Name": "Naryansingh S/O Shri Ramsingh Tanwar & Mrs. Sushila Bai W/O Narayan Singh Tanwar", "Comm Add 1": "Village Hirankhedi Post Hirankhedi", "Mobile Num": "9826336803", "Acct Opn Date": 41305.0, "Sanct Lim Amount": 60000.0, "O/S Bal": 11899.93, "Os In Dr": 0.0, "Uri": 0.0, "Os-Uri In Dr": 0.0, "Scheme Code": "LA755", "CIF NPA date": 43401.0, "Asset Code 30.09.25": 33.0, "Days": 46008.0, "UCI": 0.0, "Secured": 0.0, "Un Secured": 0.0, "Provision": 0.0, "Remarks": null}, "33075510000024": {"Acct Number": 33075510000024.0, "Sol": 3300.0, "Region": "Sehore", "Branch": "Rajgarh", "Cust Id": 999414337.0, "Acct Name": "Radhayshyam S/O Shri Bhanwar Lal Sutar & Mrs Rukmabai W/O Shri Radhayshyam Sutar", "Comm Add 1": "Village Hirankhedi Post Hirankhedi", "Mobile Num": "8889831659", "Acct Opn Date": 41316.0, "Sanct Lim Amount": 60000.0, "O/S Bal": 13231.83, "Os In Dr": 0.0, "Uri": 0.0, "Os-Uri In Dr": 0.0, "Scheme Code": "LA755", "CIF NPA date": 43462.0, "Asset Code 30.09.25": 33.0, "Days": 46008.0, "UCI": 0.0, "Secured": 0.0, "Un Secured": 0.0, "Provision": 0.0, "Remarks": null}, "33075510000016": {"Acct Number": 33075510000016.0, "Sol": 3300.0, "Region": "Sehore", "Branch": "Rajgarh", "Cust Id": 999414678.0, "Acct Name": "Phool Singh S/O Shri Amarlal Tanwar & Mrs. Krishna Bai W/O Shri Phoolsingh Tanwa", "Comm Add 1": "Village Hirankhedi Post Hirankhedi", "Mobile Num": "9826336803", "Acct Opn Date": 41305.0, "Sanct Lim Amount": 60000.0, "O/S Bal": 0.0, "Os In Dr": 0.0, "Uri": 0.0, "Os-Uri In Dr": 0.0, "Scheme Code": "LA755", "CIF NPA date": 42640.0, "Asset Code 30.09.25": 33.0, "Days": 46008.0, "UCI": 0.0, "Secured": 0.0, "Un Secured": 0.0, "Provision": 0.0, "Remarks": null}, "33075510000012": {"Acct Number": 33075510000012.0, "Sol": 3300.0, "Region": "Sehore", "Branch": "Rajgarh", "Cust Id": 999414688.0, "Acct Name": "Mangilal S/O Shri Gopilal Tanwar & Mrs. Mewa Bai W/O Shri Mangilal Tanwar", "Comm Add 1": "Village Hirankhedi Post Hirankhedi", "Mobile Num": "9826336803", "Acct Opn Date": 41305.0, "Sanct Lim Amount": 60000.0, "O/S Bal": 0.0, "Os In Dr": 0.0, "Uri": 0.0, "Os-Uri In Dr": 0.0, "Scheme Code": "LA755", "CIF NPA date": 42640.0, "Asset Code 30.09.25": 33.0, "Days": 46008.0, "UCI": 0.0, "Secured": 0.0, "Un Secured": 0.0, "Provision": 0.0, "Remarks": null}, "33075510000022": {"Acct Number": 33075510000022.0, "Sol": 3300.0, "Region": "Sehore", "Branch": "Rajgarh", "Cust Id": 999414714.0, "Acct Name": "Bapulal S/O Shri Gopilal Tanwar & Mrs. Manjubai W/O Shri Bapulal Tanwar", "Comm Add 1": "Village Hirankhedi Post Hirankhedi", "Mobile Num": "9826336803", "Acct Opn Date": 41316.0, "Sanct Lim Amount": 60000.0, "O/S Bal": 0.0, "Os In Dr": 0.0, "Uri": 0.0, "Os-Uri In Dr": 0.0, "Scheme Code": "LA755", "CIF NPA date": 42640.0, "Asset Code 30.09.25": 33.0, "Days": 46008.0, "UCI": 0.0, "Secured": 0.0, "Un Secured": 0.0, "Provision": 0.0, "Remarks": null}, "33075510000017": {"Acct Number": 33075510000017.0, "Sol": 3300.0, "Region": "Sehore", "Branch": "Rajgarh", "Cust Id": 999414722.0, "Acct Name": "Kali Bai W/O Shri Gopal Tanwar & Shri Ramchandra S/O Gopal Tanwar", "Comm Add 1": "Village Hirankhedi Post Hirankhedi", "Mobile Num": "9826336803", "Acct Opn Date": 41305.0, "Sanct Lim Amount": 60000.0, "O/S Bal": 2511.23, "Os In Dr": 0.0, "Uri": 0.0, "Os-Uri In Dr": 0.0, "Scheme Code": "LA755", "CIF NPA date": 42824.0, "Asset Code 30.09.25": 33.0, "Days": 46008.0, "UCI": 0.0, "Secured": 0.0, "Un Secured": 0.0, "Provision": 0.0, "Remarks": null}, "33075510000021": {"Acct Number": 33075510000021.0, "Sol": 3300.0, "Region": "Sehore", "Branch": "Rajgarh", "Cust Id": 999427590.0, "Acct Name": "Kamal Singh S/O Shri Raghunath Singh & Mrs. Sardar Bai W/O Raghunath Singh", "Comm Add 1": "Village Hirankhedi", "Mobile Num": "91000", "Acct Opn Date": 41314.0, "Sanct Lim Amount": 60000.0, "O/S Bal": 0.0, "Os In Dr": 0.0, "Uri": 0.0, "Os-Uri In Dr": 0.0, "Scheme Code": "LA755", "CIF NPA date": 42702.0, "Asset Code 30.09.25": 33.0, "Days": 46008.0, "UCI": 0.0, "Secured": 0.0, "Un Secured": 0.0, "Provision": 0.0, "Remarks": null}, "33035110000263": {"Acct Number": 33035110000263.0, "Sol": 3300.0, "Region": "Sehore", "Branch": "Rajgarh", "Cust Id": 999562786.0, "Acct Name": "Inder Singh S/O Shri Jaganath", "Comm Add 1": "Village Manoherpura , Post Phoolkhedi", "Mobile Num": "7898067292", "Acct Opn Date": 41449.0, "Sanct Lim Amount": 155000.0, "O/S Bal": 19963.1, "Os In Dr": 0.0, "Uri": 0.0, "Os-Uri In Dr": 0.0, "Scheme Code": "CC351", "CIF NPA date": 43190.0, "Asset Code 30.09.25": 33.0, "Days": 46008.0, "UCI": 0.0, "Secured": 0.0, "Un Secured": 0.0, "Provision": 0.0, "Remarks": null}, "33075510000058": {"Acct Number": 33075510000058.0, "Sol": 3300.0, "Region": "Sehore", "Branch": "Rajgarh", "Cust Id": 999640718.0, "Acct Name": "Ganpat Tanwar S/O Shri Ramprasad Tanwar", "Comm Add 1": "Village Rampuriya Post Hirankhedi", "Mobile Num": "91000", "Acct Opn Date": 41712.0, "Sanct Lim Amount": 100000.0, "O/S Bal": -32705.0, "Os In Dr": 32705.0, "Uri": 0.0, "Os-Uri In Dr": 32705.0, "Scheme Code": "LA755", "CIF NPA date": 42610.0, "Asset Code 30.09.25": 33.0, "Days": 46008.0, "UCI": 20551.732397260275, "Secured": 32705.0, "Un Secured": 0.0, "Provision": 32705.0, "Remarks": null}, "33070610000128": {"Acct Number": 33070610000128.0, "Sol": 3300.0, "Region": "Sehore", "Branch": "Rajgarh", "Cust Id": 999658735.0, "Acct Name": "Dinesh Sen So Roadmal Sen", "Comm Add 1": "27 / 2 , Tilak Marg Rajgarh", "Mobile Num": "9009594433", "Acct Opn Date": 45278.0, "Sanct Lim Amount": 20000.0, "O/S Bal": -13091.23, "Os In Dr": 13091.23, "Uri": 169.27, "Os-Uri In Dr": 12921.96, "Scheme Code": "LA706", "CIF NPA date": 45595.0, "Asset Code 30.09.25": 40.0, "Days": 46008.0, "UCI": 986.9368216438355, "Secured": 0.0, "Un Secured": 12921.96, "Provision": 12921.96, "Remarks": null}, "33075510000098": {"Acct Number": 33075510000098.0, "Sol": 3300.0, "Region": "Sehore", "Branch": "Rajgarh", "Cust Id": 999743908.0, "Acct Name": "Jagdish S/O Ramprasad", "Comm Add 1": "Hirankhedi Post Pipalbay", "Mobile Num": "9999999999", "Acct Opn Date": 42405.0, "Sanct Lim Amount": 100000.0, "O/S Bal": -24145.36, "Os In Dr": 24145.36, "Uri": 662.0, "Os-Uri In Dr": 23483.36, "Scheme Code": "LA755", "CIF NPA date": 45899.0, "Asset Code 30.09.25": 21.0, "Days": 46008.0, "UCI": 473.36663342465755, "Secured": 23483.36, "Un Secured": 0.0, "Provision": 2348.3360000000002, "Remarks": null}, "33075510000079": {"Acct Number": 33075510000079.0, "Sol": 3300.0, "Region": "Sehore", "Branch": "Rajgarh", "Cust Id": 999744199.0, "Acct Name": "Rod Ji S/O Deviram", "Comm Add 1": "Hirankhedi Post Pipalbay", "Mobile Num": "91000", "Acct Opn Date": 41939.0, "Sanct Lim Amount": 100000.0, "O/S Bal": 21739.86, "Os In Dr": 0.0, "Uri": 0.0, "Os-Uri In Dr": 0.0, "Scheme Code": "LA755", "CIF NPA date": 43644.0, "Asset Code 30.09.25": 33.0, "Days": 46008.0, "UCI": 0.0, "Secured": 0.0, "Un Secured": 0.0, "Provision": 0.0, "Remarks": null}, "33075510000086": {"Acct Number": 33075510000086.0, "Sol": 3300.0, "Region": "Sehore", "Branch": "Rajgarh", "Cust Id": 999744275.0, "Acct Name": "Prem Singh S/O Mangi Lal,Reshambai", "Comm Add 1": "Hirankhedi Post Pipalbay", "Mobile Num": "7297300687", "Acct Opn Date": 41941.0, "Sanct Lim Amount": 100000.0, "O/S Bal": 4584.86, "Os In Dr": 0.0, "Uri": 0.0, "Os-Uri In Dr": 0.0, "Scheme Code": "LA755", "CIF NPA date": 45135.0, "Asset Code 30.09.25": 32.0, "Days": 46008.0, "UCI": 0.0, "Secured": 0.0, "Un Secured": 0.0, "Provision": 0.0, "Remarks": null}, "33075510000091": {"Acct Number": 33075510000091.0, "Sol": 3300.0, "Region": "Sehore", "Branch": "Rajgarh", "Cust Id": 999744281.0, "Acct Name": "Kanhaiyalal S/O Dhulji Tanwar", "Comm Add 1": "Hirankhedi Post Pipalbay", "Mobile Num": "91000", "Acct Opn Date": 42405.0, "Sanct Lim Amount": 100000.0, "O/S Bal": 16241.0, "Os In Dr": 0.0, "Uri": 0.0, "Os-Uri In Dr": 0.0, "Scheme Code": "LA755", "CIF NPA date": 44101.0, "Asset Code 30.09.25": 33.0, "Days": 46008.0, "UCI": 0.0, "Secured": 0.0, "Un Secured": 0.0, "Provision": 0.0, "Remarks": null}, "33070810000009": {"Acct Number": 33070810000009.0, "Sol": 3300.0, "Region": "Sehore", "Branch": "Rajgarh", "Cust Id": 999744462.0, "Acct Name": "Arjun Singh Verma So Raghunath Singh Verma", "Comm Add 1": "Hirankhedi Post Pipalbay", "Mobile Num": "9713654048", "Acct Opn Date": 44184.0, "Sanct Lim Amount": 10000.0, "O/S Bal": -1121.0, "Os In Dr": 1121.0, "Uri": 1121.0, "Os-Uri In Dr": 0.0, "Scheme Code": "LA708", "CIF NPA date": 44832.0, "Asset Code 30.09.25": 40.0, "Days": 46008.0, "UCI": 0.0, "Secured": 0.0, "Un Secured": 0.0, "Provision": 0.0, "Remarks": null}, "33075510000102": {"Acct Number": 33075510000102.0, "Sol": 3300.0, "Region": "Sehore", "Branch": "Rajgarh", "Cust Id": 999746335.0, "Acct Name": "Biram Singh Verma S/O Ramlal Verma", "Comm Add 1": "Village Pipalbay Purohit Rajgarh", "Mobile Num": "9174246966", "Acct Opn Date": 42405.0, "Sanct Lim Amount": 100000.0, "O/S Bal": 10672.0, "Os In Dr": 0.0, "Uri": 0.0, "Os-Uri In Dr": 0.0, "Scheme Code": "LA755", "CIF NPA date": 43007.0, "Asset Code 30.09.25": 33.0, "Days": 46008.0, "UCI": 0.0, "Secured": 0.0, "Un Secured": 0.0, "Provision": 0.0, "Remarks": null}, "33075510000101": {"Acct Number": 33075510000101.0, "Sol": 3300.0, "Region": "Sehore", "Branch": "Rajgarh", "Cust Id": 999747459.0, "Acct Name": "Shivnarayan S/O Lakshminarayan Sondhiya", "Comm Add 1": "Village Pipalbay Post Hirankhedi Rajgarh", "Mobile Num": "7773026798", "Acct Opn Date": 42405.0, "Sanct Lim Amount": 100000.0, "O/S Bal": -38827.69, "Os In Dr": 38827.69, "Uri": 0.0, "Os-Uri In Dr": 38827.69, "Scheme Code": "LA755", "CIF NPA date": 45380.0, "Asset Code 30.09.25": 31.0, "Days": 46008.0, "UCI": 4509.330901643836, "Secured": 38827.69, "Un Secured": 0.0, "Provision": 7765.5380000000005, "Remarks": null}, "33065710000098": {"Acct Number": 33065710000098.0, "Sol": 3300.0, "Region": "Sehore", "Branch": "Rajgarh", "Cust Id": 999747459.0, "Acct Name": "Shivnarayan Chouhan S/O Lakshminarayan", "Comm Add 1": "Village Pipalbay Post Hirankhedi Rajgarh", "Mobile Num": "7773026798", "Acct Opn Date": 44460.0, "Sanct Lim Amount": 23000.0, "O/S Bal": -9046.0, "Os In Dr": 9046.0, "Uri": 0.0, "Os-Uri In Dr": 9046.0, "Scheme Code": "LA657", "CIF NPA date": 45380.0, "Asset Code 30.09.25": 31.0, "Days": 46008.0, "UCI": 1050.5751780821918, "Secured": 9046.0, "Un Secured": 0.0, "Provision": 1809.2, "Remarks": null}, "33075510000055": {"Acct Number": 33075510000055.0, "Sol": 3300.0, "Region": "Sehore", "Branch": "Rajgarh", "Cust Id": 999836884.0, "Acct Name": "Amarsingh S/O Nagaji And Jagdish S/O Amarsingh", "Comm Add 1": "Village Daftari Post Hirankhedi", "Mobile Num": "9098930349", "Acct Opn Date": 41709.0, "Sanct Lim Amount": 100000.0, "O/S Bal": -14752.0, "Os In Dr": 14752.0, "Uri": 0.0, "Os-Uri In Dr": 14752.0, "Scheme Code": "LA755", "CIF NPA date": 42763.0, "Asset Code 30.09.25": 33.0, "Days": 46008.0, "UCI": 8852.715616438356, "Secured": 14752.0, "Un Secured": 0.0, "Provision": 14752.0, "Remarks": null}, "33075510000050": {"Acct Number": 33075510000050.0, "Sol": 3300.0, "Region": "Sehore", "Branch": "Rajgarh", "Cust Id": 999837053.0, "Acct Name": "Rodji S/O Bapulal And Kantibai W/O Rodji", "Comm Add 1": "Village Daftari Post Hirankhedi", "Mobile Num": "91000", "Acct Opn Date": 41704.0, "Sanct Lim Amount": 100000.0, "O/S Bal": -35694.93, "Os In Dr": 35694.93, "Uri": 0.0, "Os-Uri In Dr": 35694.93, "Scheme Code": "LA755", "CIF NPA date": 45806.0, "Asset Code 30.09.25": 21.0, "Days": 46008.0, "UCI": 1333.425672739726, "Secured": 35694.93, "Un Secured": 0.0, "Provision": 3569.4930000000004, "Remarks": null}, "33065710000042": {"Acct Number": 33065710000042.0, "Sol": 3300.0, "Region": "Sehore", "Branch": "Rajgarh", "Cust Id": 999837053.0, "Acct Name": "Rodji S/O Bapulal And Kantibai W/O Rodji", "Comm Add 1": "Village Daftari Post Hirankhedi", "Mobile Num": "91000", "Acct Opn Date": 44372.0, "Sanct Lim Amount": 25000.0, "O/S Bal": -15159.52, "Os In Dr": 15159.52, "Uri": 528.0, "Os-Uri In Dr": 14631.52, "Scheme Code": "LA657", "CIF NPA date": 45806.0, "Asset Code 30.09.25": 21.0, "Days": 46008.0, "UCI": 546.57746630137, "Secured": 14631.52, "Un Secured": 0.0, "Provision": 1463.152, "Remarks": null}, "33075510000056": {"Acct Number": 33075510000056.0, "Sol": 3300.0, "Region": "Sehore", "Branch": "Rajgarh", "Cust Id": 999839873.0, "Acct Name": "Ramesh S/O Maansingh And Sumitrabai W/O Ramesh", "Comm Add 1": "Village Dand, Post Hirankhedi", "Mobile Num": "91000", "Acct Opn Date": 41712.0, "Sanct Lim Amount": 100000.0, "O/S Bal": -19924.0, "Os In Dr": 19924.0, "Uri": 0.0, "Os-Uri In Dr": 19924.0, "Scheme Code": "LA755", "CIF NPA date": 42975.0, "Asset Code 30.09.25": 33.0, "Days": 46008.0, "UCI": 11175.31701369863, "Secured": 19924.0, "Un Secured": 0.0, "Provision": 19924.0, "Remarks": null}, "33075510000115": {"Acct Number": 33075510000115.0, "Sol": 3300.0, "Region": "Sehore", "Branch": "Rajgarh", "Cust Id": 999884158.0, "Acct Name": "Mor Singh S/O Kanhaiyalal,Rekha Bai W/O Morsingh", "Comm Add 1": "Gram Hirankhedi Rajgarh", "Mobile Num": "91000", "Acct Opn Date": 42500.0, "Sanct Lim Amount": 100000.0, "O/S Bal": -24503.0, "Os In Dr": 24503.0, "Uri": 0.0, "Os-Uri In Dr": 24503.0, "Scheme Code": "LA755", "CIF NPA date": 43644.0, "Asset Code 30.09.25": 33.0, "Days": 46008.0, "UCI": 10712.174547945206, "Secured": 24503.0, "Un Secured": 0.0, "Provision": 24503.0, "Remarks": null}, "33075510000077": {"Acct Number": 33075510000077.0, "Sol": 3300.0, "Region": "Sehore", "Branch": "Rajgarh", "Cust Id": 999885615.0, "Acct Name": "Dhulaji So Gopeelal", "Comm Add 1": "Gram& Post Hirankhedi", "Mobile Num": "91000", "Acct Opn Date": 41939.0, "Sanct Lim Amount": 100000.0, "O/S Bal": 10496.0, "Os In Dr": 0.0, "Uri": 0.0, "Os-Uri In Dr": 0.0, "Scheme Code": "LA755", "CIF NPA date": 43462.0, "Asset Code 30.09.25": 33.0, "Days": 46008.0, "UCI": 0.0, "Secured": 0.0, "Un Secured": 0.0, "Provision": 0.0, "Remarks": null}, "33075510000085": {"Acct Number": 33075510000085.0, "Sol": 3300.0, "Region": "Sehore", "Branch": "Rajgarh", "Cust Id": 999885626.0, "Acct Name": "Kamal So Gorelal", "Comm Add 1": "Gram& Post Hirankhedi", "Mobile Num": "91000", "Acct Opn Date": 41941.0, "Sanct Lim Amount": 100000.0, "O/S Bal": 33516.87, "Os In Dr": 0.0, "Uri": 0.0, "Os-Uri In Dr": 0.0, "Scheme Code": "LA755", "CIF NPA date": 43279.0, "Asset Code 30.09.25": 33.0, "Days": 46008.0, "UCI": 0.0, "Secured": 0.0, "Un Secured": 0.0, "Provision": 0.0, "Remarks": null}, "33075510000092": {"Acct Number": 33075510000092.0, "Sol": 3300.0, "Region": "Sehore", "Branch": "Rajgarh", "Cust Id": 999885636.0, "Acct Name": "Kamala Bai W/O Ramsingh Tanwar", "Comm Add 1": "Gram& Post Hirankhedi", "Mobile Num": "91000", "Acct Opn Date": 42405.0, "Sanct Lim Amount": 100000.0, "O/S Bal": 16278.84, "Os In Dr": 0.0, "Uri": 0.0, "Os-Uri In Dr": 0.0, "Scheme Code": "LA755", "CIF NPA date": 43279.0, "Asset Code 30.09.25": 33.0, "Days": 46008.0, "UCI": 0.0, "Secured": 0.0, "Un Secured": 0.0, "Provision": 0.0, "Remarks": null}, "33075510000110": {"Acct Number": 33075510000110.0, "Sol": 3300.0, "Region": "Sehore", "Branch": "Rajgarh", "Cust Id": 999885651.0, "Acct Name": "Chainsingh S/O Narayan Tanwar", "Comm Add 1": "Gram& Post Hirankhedi", "Mobile Num": "91000", "Acct Opn Date": 42481.0, "Sanct Lim Amount": 100000.0, "O/S Bal": -22779.0, "Os In Dr": 22779.0, "Uri": 0.0, "Os-Uri In Dr": 22779.0, "Scheme Code": "LA755", "CIF NPA date": 43432.0, "Asset Code 30.09.25": 33.0, "Days": 46008.0, "UCI": 10851.541150684932, "Secured": 22779.0, "Un Secured": 0.0, "Provision": 22779.0, "Remarks": null}, "33075510000095": {"Acct Number": 33075510000095.0, "Sol": 3300.0, "Region": "Sehore", "Branch": "Rajgarh", "Cust Id": 999885676.0, "Acct Name": "Mohanlal So Kanhaiyalal", "Comm Add 1": "Gram& Post Hirankhedi", "Mobile Num": "9713875370", "Acct Opn Date": 42405.0, "Sanct Lim Amount": 100000.0, "O/S Bal": 13042.57, "Os In Dr": 0.0, "Uri": 0.0, "Os-Uri In Dr": 0.0, "Scheme Code": "LA755", "CIF NPA date": 43279.0, "Asset Code 30.09.25": 33.0, "Days": 46008.0, "UCI": 0.0, "Secured": 0.0, "Un Secured": 0.0, "Provision": 0.0, "Remarks": null}, "33075510000096": {"Acct Number": 33075510000096.0, "Sol": 3300.0, "Region": "Sehore", "Branch": "Rajgarh", "Cust Id": 999887620.0, "Acct Name": "Phool Singh S/O Madanlal Tanwar", "Comm Add 1": "Gram& Post Hirankhedi", "Mobile Num": "91000", "Acct Opn Date": 42405.0, "Sanct Lim Amount": 100000.0, "O/S Bal": 32304.0, "Os In Dr": 0.0, "Uri": 0.0, "Os-Uri In Dr": 0.0, "Scheme Code": "LA755", "CIF NPA date": 43644.0, "Asset Code 30.09.25": 33.0, "Days": 46008.0, "UCI": 0.0, "Secured": 0.0, "Un Secured": 0.0, "Provision": 0.0, "Remarks": null}, "33075510000078": {"Acct Number": 33075510000078.0, "Sol": 3300.0, "Region": "Sehore", "Branch": "Rajgarh", "Cust Id": 999890974.0, "Acct Name": "Gendalal So Amara", "Comm Add 1": "Gram &I Post Hirankhedi", "Mobile Num": "91000", "Acct Opn Date": 41939.0, "Sanct Lim Amount": 100000.0, "O/S Bal": 10496.0, "Os In Dr": 0.0, "Uri": 0.0, "Os-Uri In Dr": 0.0, "Scheme Code": "LA755", "CIF NPA date": 43462.0, "Asset Code 30.09.25": 33.0, "Days": 46008.0, "UCI": 0.0, "Secured": 0.0, "Un Secured": 0.0, "Provision": 0.0, "Remarks": null}, "33075510000080": {"Acct Number": 33075510000080.0, "Sol": 3300.0, "Region": "Sehore", "Branch": "Rajgarh", "Cust Id": 999891008.0, "Acct Name": "Chenasingh So Deviram", "Comm Add 1": "Gram &I Post Hirankhedi", "Mobile Num": "91000", "Acct Opn Date": 41939.0, "Sanct Lim Amount": 100000.0, "O/S Bal": 18688.91, "Os In Dr": 0.0, "Uri": 0.0, "Os-Uri In Dr": 0.0, "Scheme Code": "LA755", "CIF NPA date": 43462.0, "Asset Code 30.09.25": 33.0, "Days": 46008.0, "UCI": 0.0, "Secured": 0.0, "Un Secured": 0.0, "Provision": 0.0, "Remarks": null}, "33075510000107": {"Acct Number": 33075510000107.0, "Sol": 3300.0, "Region": "Sehore", "Branch": "Rajgarh", "Cust Id": 999978270.0, "Acct Name": "Babu Lal S/O Dev Chand Valmiki", "Comm Add 1": "Village-Hiran Khedi", "Mobile Num": "91000", "Acct Opn Date": 42473.0, "Sanct Lim Amount": 100000.0, "O/S Bal": 10352.0, "Os In Dr": 0.0, "Uri": 0.0, "Os-Uri In Dr": 0.0, "Scheme Code": "LA755", "CIF NPA date": 43005.0, "Asset Code 30.09.25": 33.0, "Days": 46008.0, "UCI": 0.0, "Secured": 0.0, "Un Secured": 0.0, "Provision": 0.0, "Remarks": null}, "33075510000074": {"Acct Number": 33075510000074.0, "Sol": 3300.0, "Region": "Sehore", "Branch": "Rajgarh", "Cust Id": 999986311.0, "Acct Name": "Kamal Singh S/O Narayan & Mangibai W/O Kamalsingh Tanwar", "Comm Add 1": "Gram& Post Hirankhedi", "Mobile Num": "7566857663", "Acct Opn Date": 41856.0, "Sanct Lim Amount": 100000.0, "O/S Bal": -31314.0, "Os In Dr": 31314.0, "Uri": 0.0, "Os-Uri In Dr": 31314.0, "Scheme Code": "LA755", "CIF NPA date": 43067.0, "Asset Code 30.09.25": 33.0, "Days": 46008.0, "UCI": 17031.16984931507, "Secured": 31314.0, "Un Secured": 0.0, "Provision": 31314.0, "Remarks": null}}